connect_extension_utils/__init__.py
connect_extension_utils/api/__init__.py
connect_extension_utils/api/errors.py
connect_extension_utils/api/pagination.py
connect_extension_utils/api/schemas.py
connect_extension_utils/api/views.py
connect_extension_utils/connect_services/__init__.py
connect_extension_utils/connect_services/base.py
connect_extension_utils/db/__init__.py
connect_extension_utils/db/models.py
connect_extension_utils/testing/__init__.py
connect_extension_utils/testing/database.py
connect_extension_utils/testing/factories.py
connect_extension_utils/testing/fixtures.py
connect_extension_utils-1.3.0.dist-info/LICENSE
connect_extension_utils-1.3.0.dist-info/METADATA
connect_extension_utils-1.3.0.dist-info/WHEEL
connect_extension_utils-1.3.0.dist-info/entry_points.txt
connect_extension_utils-1.3.0.dist-info/RECORD
